vsflip.py
vsflip-1.1.0.dist-info/licenses/LICENSE
vsflip-1.1.0.dist-info/METADATA
vsflip-1.1.0.dist-info/WHEEL
vsflip-1.1.0.dist-info/top_level.txt
vsflip-1.1.0.dist-info/RECORD
