Metadata-Version: 2.4
Name: vsflip
Version: 1.1.0
Summary: A VapourSynth wrapper for the FLIP perceptual metric
Author-email: PingWer <r74michele@gmail.com>
License: MIT License
Requires-Python: >=3.13
License-File: LICENSE
Requires-Dist: numpy
Requires-Dist: matplotlib
Requires-Dist: flip_evaluator
Requires-Dist: vapoursynth
Dynamic: license-file
